{"cameraMode":{"drawMode":0,"name":"Shaded","section":"Shading Mode"},"sceneLighting":true,"audioPlay":false,"sceneViewState":{"m_AlwaysRefresh":false,"showFog":true,"showSkybox":true,"showFlares":true,"showImageEffects":true,"showParticleSystems":true,"showVisualEffectGraphs":true,"m_FxEnabled":true},"in2DMode":false,"pivot":{"x":-0.774371862411499,"y":-1.1056984663009644,"z":-11.804218292236329},"rotation":{"x":0.0028390143997967245,"y":0.985479474067688,"z":-0.1689712554216385,"w":0.01655908115208149},"size":4.304854869842529,"orthographic":false}